miind-1.0.21.dist-info/METADATA
miind-1.0.21.dist-info/LICENSE
miind-1.0.21.dist-info/WHEEL
miind-1.0.21.dist-info/top_level.txt
miind-1.0.21.dist-info/RECORD
miind.libs/libboost_system-mt-da72321c.so.1.53.0
miind.libs/libgomp-a34b3233.so.1.0.0
miind.libs/libboost_thread-mt-80251d3d.so.1.53.0
miind.libs/libboost_date_time-mt-3d7d21d8.so.1.53.0
miind.libs/libsatlas-7e2f78d2.so.3.10
miind.libs/libquadmath-96973f99.so.0.0.0
miind.libs/libglut-b0f599c2.so.3.10.0
miind.libs/libgsl-cb3064f9.so.0.16.0
miind.libs/libboost_chrono-mt-598921be.so.1.53.0
miind.libs/libXxf86vm-3971cbbb.so.1.0.0
miind.libs/libboost_timer-mt-4f8126c3.so.1.53.0
miind.libs/libXi-e28fba09.so.6.1.0
miind.libs/libgfortran-91cc3cb1.so.3.0.0
miind.libs/libboost_filesystem-mt-c869e5cd.so.1.53.0
miind.libs/libGLU-03ef17d1.so.1.3.1
miind.libs/libgslcblas-9055a056.so.0.0.0
miind.libs/libboost_atomic-mt-c860e9ce.so.1.53.0
miind.libs/libboost_unit_test_framework-mt-60f68019.so.1.53.0
miind.libs/libboost_serialization-mt-a5edaee0.so.1.53.0
miind.libs/libboost_program_options-mt-4c221024.so.1.53.0
miind/submit.py
miind/__init__.py
miind/miind_lib.py
miind/cmake_template_lib
miind/nodes.py
miind/launch.py
miind/TvbMiindModel.py
miind/directories3.py
miind/jobs.py
miind/miind_settings
miind/codegen3.py
miind/run.py
miind/simulation.py
miind/loadExamples.py
miind/miindio.py
miind/lost.py
miind/miindrun.py
miind/ode2dsystem.py
miind/visualize.py
miind/miindsimv.so
miind/writemesh.py
miind/bary.py
miind/system_tests.py
miind/palette.py
miind/include.py
miind/mesh3.py
miind/cmake_template
miind/grid_rybak.py
miind/grid_fn.py
miind/miindTVBlibs.py
miind/codegen_lib.py
miind/demo2D.py
miind/meshtest3.py
miind/mesh.py
miind/miindsim.so
miind/utilities.py
miind/reporting.py
miind/parametersweep.py
miind/variables.py
miind/grid_cond.py
miind/bary3.py
miind/directories.py
miind/algorithms.py
miind/peakdetect.py
miind/grid_adex.py
miind/grid_generate_nd.py
miind/checkMatrixGenerator.py
miind/grid_generate.py
miind/codegen_lib3.py
miind/connections.py
miind/codegen.py
miind/miindgen.so
miind/sub.sh
