Metadata-Version: 2.1
Name: miind
Version: 1.0.21
Summary: MIIND
Home-page: https://github.com/dekamps/miind
Classifier: Programming Language :: Python
Classifier: Programming Language :: Python :: 3
Classifier: Programming Language :: Python :: 3 :: Only
Classifier: Programming Language :: Python :: 3.6
Classifier: Programming Language :: Python :: 3.7
Classifier: Programming Language :: Python :: 3.8
Classifier: Programming Language :: Python :: 3.9
Classifier: Operating System :: MacOS
Classifier: Operating System :: Unix
Classifier: Operating System :: Microsoft :: Windows
Requires-Python: >=3.6
License-File: LICENSE
Requires-Dist: shapely
Requires-Dist: descartes
Requires-Dist: numpy
Requires-Dist: matplotlib
Requires-Dist: scipy
